<?xml version="1.0" encoding="UTF-8"?>
<config ref="Beta_SiteList_010408_v8_BSIDVerified(dist).xls">
	<bases name="Portland Beta">
		<base name="POR002_A" frequency="2553000" color="#FF33CC" baseid="000002000001" latitude="45.522625" longitude="-123.103245" azimuth="80"/>
		<base name="POR002_B" frequency="2573000" color="#FFFF99" baseid="000002000002" latitude="45.522625" longitude="-123.103245" azimuth="180"/>
		<base name="POR002_C" frequency="2583000" color="#CCFFFF" baseid="000002000003" latitude="45.522625" longitude="-123.103245" azimuth="300"/>
		<base name="POR003_A" frequency="2553000" color="#FF33CC" baseid="00000200001B" latitude="45.52454" longitude="-123.079845" azimuth="80"/>
		<base name="POR003_B" frequency="2573000" color="#FFFF99" baseid="000002000019" latitude="45.52454" longitude="-123.079845" azimuth="170"/>
		<base name="POR003_C" frequency="2583000" color="#CCFFFF" baseid="00000200001A" latitude="45.52454" longitude="-123.079845" azimuth="280"/>
		<base name="POR004_A" frequency="2553000" color="#FF33CC" baseid="000002000032" latitude="45.52248" longitude="-123.04896" azimuth="100"/>
		<base name="POR004_B" frequency="2573000" color="#FFFF99" baseid="000002000033" latitude="45.52248" longitude="-123.04896" azimuth="180"/>
		<base name="POR004_C" frequency="2583000" color="#CCFFFF" baseid="000002000031" latitude="45.52248" longitude="-123.04896" azimuth="280"/>
		<base name="POR008_A" frequency="2553000" color="#FF33CC" baseid="000002000049" latitude="45.521917" longitude="-122.99297" azimuth="80"/>
		<base name="POR008_B" frequency="2573000" color="#FFFF99" baseid="00000200004A" latitude="45.521917" longitude="-122.99297" azimuth="200"/>
		<base name="POR008_C" frequency="2583000" color="#CCFFFF" baseid="00000200004B" latitude="45.521917" longitude="-122.99297" azimuth="340"/>
		<base name="POR009_A" frequency="2553000" color="#FF33CC" baseid="000002000091" latitude="45.543448" longitude="-122.96389" azimuth="60"/>
		<base name="POR009_B" frequency="2573000" color="#FFFF99" baseid="000002000092" latitude="45.543448" longitude="-122.96389" azimuth="180"/>
		<base name="POR009_C" frequency="2583000" color="#CCFFFF" baseid="000002000093" latitude="45.543448" longitude="-122.96389" azimuth="280"/>
		<base name="POR010_A" frequency="2553000" color="#FF33CC" baseid="00000200007A" latitude="45.528278" longitude="-122.97094" azimuth="60"/>
		<base name="POR010_B" frequency="2573000" color="#FFFF99" baseid="00000200007B" latitude="45.528278" longitude="-122.97094" azimuth="180"/>
		<base name="POR010_C" frequency="2583000" color="#CCFFFF" baseid="000002000079" latitude="45.528278" longitude="-122.97094" azimuth="300"/>
		<base name="POR011_A" frequency="2553000" color="#FF33CC" baseid="000002000063" latitude="45.5201" longitude="-122.976" azimuth="90"/>
		<base name="POR011_B" frequency="2573000" color="#FFFF99" baseid="000002000061" latitude="45.5201" longitude="-122.976" azimuth="180"/>
		<base name="POR011_C" frequency="2583000" color="#CCFFFF" baseid="000002000062" latitude="45.5201" longitude="-122.976" azimuth="300"/>
		<base name="POR015_A" frequency="2553000" color="#FF33CC" baseid="0000020000C3" latitude="45.532761" longitude="-122.93479" azimuth="60"/>
		<base name="POR015_B" frequency="2573000" color="#FFFF99" baseid="0000020000C1" latitude="45.532761" longitude="-122.93479" azimuth="200"/>
		<base name="POR015_C" frequency="2583000" color="#CCFFFF" baseid="0000020000C2" latitude="45.532761" longitude="-122.93479" azimuth="300"/>
		<base name="POR018_A" frequency="2553000" color="#FF33CC" baseid="0000020000F3" latitude="45.558028" longitude="-122.90467" azimuth="60"/>
		<base name="POR018_B" frequency="2573000" color="#FFFF99" baseid="0000020000F1" latitude="45.558028" longitude="-122.90467" azimuth="180"/>
		<base name="POR018_C" frequency="2583000" color="#CCFFFF" baseid="0000020000F2" latitude="45.558028" longitude="-122.90467" azimuth="270"/>
		<base name="POR019_A" frequency="2553000" color="#FF33CC" baseid="0000020000DA" latitude="45.53125" longitude="-122.9087" azimuth="60"/>
		<base name="POR019_B" frequency="2573000" color="#FFFF99" baseid="0000020000DB" latitude="45.53125" longitude="-122.9087" azimuth="200"/>
		<base name="POR019_C" frequency="2583000" color="#CCFFFF" baseid="0000020000D9" latitude="45.53125" longitude="-122.9087" azimuth="300"/>
		<base name="POR021_A" frequency="2553000" color="#FF33CC" baseid="0000020000A9" latitude="45.5035" longitude="-122.9507" azimuth="70"/>
		<base name="POR021_B" frequency="2573000" color="#FFFF99" baseid="0000020000AA" latitude="45.5035" longitude="-122.9507" azimuth="220"/>
		<base name="POR021_C" frequency="2583000" color="#CCFFFF" baseid="0000020000AB" latitude="45.5035" longitude="-122.9507" azimuth="300"/>
		<base name="POR025_A" frequency="2553000" color="#FF33CC" baseid="000002000009" latitude="45.52365" longitude="-122.89808" azimuth="50"/>
		<base name="POR025_B" frequency="2573000" color="#FFFF99" baseid="00000200000A" latitude="45.52365" longitude="-122.89808" azimuth="160"/>
		<base name="POR025_C" frequency="2583000" color="#CCFFFF" baseid="00000200000B" latitude="45.52365" longitude="-122.89808" azimuth="300"/>
		<base name="POR026_A" frequency="2553000" color="#FF33CC" baseid="00000200003A" latitude="45.498517" longitude="-122.91471" azimuth="60"/>
		<base name="POR026_B" frequency="2573000" color="#FFFF99" baseid="00000200003B" latitude="45.498517" longitude="-122.91471" azimuth="180"/>
		<base name="POR026_C" frequency="2583000" color="#CCFFFF" baseid="000002000039" latitude="45.498517" longitude="-122.91471" azimuth="330"/>
		<base name="POR027_A" frequency="2553000" color="#FF33CC" baseid="000002000023" latitude="45.51602" longitude="-122.902207" azimuth="60"/>
		<base name="POR027_B" frequency="2573000" color="#FFFF99" baseid="000002000021" latitude="45.51602" longitude="-122.902207" azimuth="180"/>
		<base name="POR027_C" frequency="2583000" color="#CCFFFF" baseid="000002000022" latitude="45.51602" longitude="-122.902207" azimuth="270"/>
		<base name="POR028_A" frequency="2553000" color="#FF33CC" baseid="000002000051" latitude="45.543606" longitude="-122.86708" azimuth="60"/>
		<base name="POR028_B" frequency="2573000" color="#FFFF99" baseid="000002000052" latitude="45.543606" longitude="-122.86708" azimuth="220"/>
		<base name="POR028_C" frequency="2583000" color="#CCFFFF" baseid="000002000053" latitude="45.543606" longitude="-122.86708" azimuth="310"/>
		<base name="POR030_A" frequency="2553000" color="#FF33CC" baseid="00000200006B" latitude="45.5236" longitude="-122.87028" azimuth="40"/>
		<base name="POR030_B" frequency="2573000" color="#FFFF99" baseid="000002000069" latitude="45.5236" longitude="-122.87028" azimuth="180"/>
		<base name="POR030_C" frequency="2583000" color="#CCFFFF" baseid="00000200006A" latitude="45.5236" longitude="-122.87028" azimuth="300"/>
		<base name="POR032_A" frequency="2553000" color="#FF33CC" baseid="000002000082" latitude="45.534142" longitude="-122.849584" azimuth="60"/>
		<base name="POR032_B" frequency="2573000" color="#FFFF99" baseid="000002000083" latitude="45.534142" longitude="-122.849584" azimuth="180"/>
		<base name="POR032_C" frequency="2583000" color="#CCFFFF" baseid="000002000081" latitude="45.534142" longitude="-122.849584" azimuth="300"/>
		<base name="POR033_A" frequency="2553000" color="#FF33CC" baseid="000002000099" latitude="45.492536" longitude="-122.89043" azimuth="60"/>
		<base name="POR033_B" frequency="2573000" color="#FFFF99" baseid="00000200009A" latitude="45.492536" longitude="-122.89043" azimuth="170"/>
		<base name="POR033_C" frequency="2583000" color="#CCFFFF" baseid="00000200009B" latitude="45.492536" longitude="-122.89043" azimuth="330"/>
		<base name="POR038_A" frequency="2553000" color="#FF33CC" baseid="0000020000B3" latitude="45.4942" longitude="-122.867" azimuth="60"/>
		<base name="POR038_B" frequency="2573000" color="#FFFF99" baseid="0000020000B1" latitude="45.4942" longitude="-122.867" azimuth="180"/>
		<base name="POR038_C" frequency="2583000" color="#CCFFFF" baseid="0000020000B2" latitude="45.4942" longitude="-122.867" azimuth="330"/>
		<base name="POR039_A" frequency="2553000" color="#FF33CC" baseid="0000020000C9" latitude="45.50635" longitude="-122.8422" azimuth="45"/>
		<base name="POR039_B" frequency="2573000" color="#FFFF99" baseid="0000020000CA" latitude="45.50635" longitude="-122.8422" azimuth="140"/>
		<base name="POR039_C" frequency="2583000" color="#CCFFFF" baseid="0000020000CB" latitude="45.50635" longitude="-122.8422" azimuth="280"/>
		<base name="POR041_A" frequency="2553000" color="#FF33CC" baseid="000002000102" latitude="45.471157" longitude="-122.881214" azimuth="45"/>
		<base name="POR041_B" frequency="2573000" color="#FFFF99" baseid="000002000103" latitude="45.471157" longitude="-122.881214" azimuth="160"/>
		<base name="POR041_C" frequency="2583000" color="#CCFFFF" baseid="000002000101" latitude="45.471157" longitude="-122.881214" azimuth="300"/>
		<base name="POR043_A" frequency="2553000" color="#FF33CC" baseid="0000020000E3" latitude="45.524458" longitude="-122.81954" azimuth="60"/>
		<base name="POR043_B" frequency="2573000" color="#FFFF99" baseid="0000020000E1" latitude="45.524458" longitude="-122.81954" azimuth="180"/>
		<base name="POR043_C" frequency="2583000" color="#CCFFFF" baseid="0000020000E2" latitude="45.524458" longitude="-122.81954" azimuth="300"/>
		<base name="POR049_A" frequency="2553000" color="#FF33CC" baseid="000002000149" latitude="45.490025" longitude="-122.82395" azimuth="80"/>
		<base name="POR049_B" frequency="2573000" color="#FFFF99" baseid="00000200014A" latitude="45.490025" longitude="-122.82395" azimuth="220"/>
		<base name="POR049_C" frequency="2583000" color="#CCFFFF" baseid="00000200014B" latitude="45.490025" longitude="-122.82395" azimuth="320"/>
		<base name="POR052_A" frequency="2553000" color="#FF33CC" baseid="000002000163" latitude="45.500481" longitude="-122.804421" azimuth="60"/>
		<base name="POR052_B" frequency="2573000" color="#FFFF99" baseid="000002000161" latitude="45.500481" longitude="-122.804421" azimuth="180"/>
		<base name="POR052_C" frequency="2583000" color="#CCFFFF" baseid="000002000162" latitude="45.500481" longitude="-122.804421" azimuth="300"/>
		<base name="POR053_A" frequency="2553000" color="#FF33CC" baseid="00000200017A" latitude="45.506534" longitude="-122.780822" azimuth="60"/>
		<base name="POR053_B" frequency="2573000" color="#FFFF99" baseid="00000200017B" latitude="45.506534" longitude="-122.780822" azimuth="180"/>
		<base name="POR053_C" frequency="2583000" color="#CCFFFF" baseid="000002000179" latitude="45.506534" longitude="-122.780822" azimuth="300"/>
		<base name="POR054_A" frequency="2553000" color="#FF33CC" baseid="000002000132" latitude="45.458033" longitude="-122.8267" azimuth="40"/>
		<base name="POR054_B" frequency="2573000" color="#FFFF99" baseid="000002000133" latitude="45.458033" longitude="-122.8267" azimuth="180"/>
		<base name="POR054_C" frequency="2583000" color="#CCFFFF" baseid="000002000131" latitude="45.458033" longitude="-122.8267" azimuth="270"/>
		<base name="POR056_A" frequency="2553000" color="#FF33CC" baseid="00000200011B" latitude="45.426294" longitude="-122.848303" azimuth="45"/>
		<base name="POR056_B" frequency="2573000" color="#FFFF99" baseid="000002000119" latitude="45.426294" longitude="-122.848303" azimuth="110"/>
		<base name="POR056_C" frequency="2583000" color="#CCFFFF" baseid="00000200011A" latitude="45.426294" longitude="-122.848303" azimuth="270"/>
		<base name="POR057_A" frequency="2553000" color="#FF33CC" baseid="000002000192" latitude="45.481811" longitude="-122.78499" azimuth="75"/>
		<base name="POR057_B" frequency="2573000" color="#FFFF99" baseid="000002000193" latitude="45.481811" longitude="-122.78499" azimuth="200"/>
		<base name="POR057_C" frequency="2583000" color="#CCFFFF" baseid="000002000191" latitude="45.481811" longitude="-122.78499" azimuth="320"/>
		<base name="POR058_A" frequency="2553000" color="#FF33CC" baseid="0000020001C1" latitude="45.442836" longitude="-122.8036" azimuth="90"/>
		<base name="POR058_B" frequency="2573000" color="#FFFF99" baseid="0000020001C2" latitude="45.442836" longitude="-122.8036" azimuth="220"/>
		<base name="POR058_C" frequency="2583000" color="#CCFFFF" baseid="0000020001C3" latitude="45.442836" longitude="-122.8036" azimuth="320"/>
		<base name="POR060_A" frequency="2553000" color="#FF33CC" baseid="0000020001AB" latitude="45.454682" longitude="-122.781196" azimuth="40"/>
		<base name="POR060_B" frequency="2573000" color="#FFFF99" baseid="0000020001A9" latitude="45.454682" longitude="-122.781196" azimuth="160"/>
		<base name="POR060_C" frequency="2583000" color="#CCFFFF" baseid="0000020001AA" latitude="45.454682" longitude="-122.781196" azimuth="290"/>
		<base name="POR061_A" frequency="2553000" color="#FF33CC" baseid="0000020001F1" latitude="45.4832" longitude="-122.754" azimuth="60"/>
		<base name="POR061_B" frequency="2573000" color="#FFFF99" baseid="0000020001F2" latitude="45.4832" longitude="-122.754" azimuth="180"/>
		<base name="POR061_C" frequency="2583000" color="#CCFFFF" baseid="0000020001F3" latitude="45.4832" longitude="-122.754" azimuth="320"/>
		<base name="POR063_A" frequency="2553000" color="#FF33CC" baseid="00000200010A" latitude="45.46679" longitude="-122.75295" azimuth="45"/>
		<base name="POR063_B" frequency="2573000" color="#FFFF99" baseid="00000200010B" latitude="45.46679" longitude="-122.75295" azimuth="170"/>
		<base name="POR063_C" frequency="2583000" color="#CCFFFF" baseid="000002000109" latitude="45.46679" longitude="-122.75295" azimuth="260"/>
		<base name="POR064_A" frequency="2553000" color="#FF33CC" baseid="0000020001B3" latitude="45.48608" longitude="-122.72218" azimuth="40"/>
		<base name="POR064_B" frequency="2573000" color="#FFFF99" baseid="0000020001B1" latitude="45.48608" longitude="-122.72218" azimuth="120"/>
		<base name="POR064_C" frequency="2583000" color="#CCFFFF" baseid="0000020001B2" latitude="45.48608" longitude="-122.72218" azimuth="280"/>
		<base name="POR065_A" frequency="2553000" color="#FF33CC" baseid="000002000283" latitude="45.420597" longitude="-122.78398" azimuth="70"/>
		<base name="POR065_B" frequency="2573000" color="#FFFF99" baseid="000002000281" latitude="45.420597" longitude="-122.78398" azimuth="210"/>
		<base name="POR065_C" frequency="2583000" color="#CCFFFF" baseid="000002000282" latitude="45.420597" longitude="-122.78398" azimuth="320"/>
		<base name="POR067_A" frequency="2553000" color="#FF33CC" baseid="00000200013A" latitude="45.43504" longitude="-122.75922" azimuth="20"/>
		<base name="POR067_B" frequency="2573000" color="#FFFF99" baseid="00000200013B" latitude="45.43504" longitude="-122.75922" azimuth="120"/>
		<base name="POR067_C" frequency="2583000" color="#CCFFFF" baseid="000002000139" latitude="45.43504" longitude="-122.75922" azimuth="270"/>
		<base name="POR068_A" frequency="2553000" color="#FF33CC" baseid="000002000151" latitude="45.46696" longitude="-122.72275" azimuth="40"/>
		<base name="POR068_B" frequency="2573000" color="#FFFF99" baseid="000002000152" latitude="45.46696" longitude="-122.72275" azimuth="200"/>
		<base name="POR068_C" frequency="2583000" color="#CCFFFF" baseid="000002000153" latitude="45.46696" longitude="-122.72275" azimuth="320"/>
		<base name="POR072_A" frequency="2553000" color="#FF33CC" baseid="0000020001DA" latitude="45.40266" longitude="-122.76368" azimuth="40"/>
		<base name="POR072_B" frequency="2573000" color="#FFFF99" baseid="0000020001DB" latitude="45.40266" longitude="-122.76368" azimuth="230"/>
		<base name="POR072_C" frequency="2583000" color="#CCFFFF" baseid="0000020001D9" latitude="45.40266" longitude="-122.76368" azimuth="310"/>
		<base name="POR074_A" frequency="2553000" color="#FF33CC" baseid="000002000169" latitude="45.419817" longitude="-122.74576" azimuth="40"/>
		<base name="POR074_B" frequency="2573000" color="#FFFF99" baseid="00000200016A" latitude="45.419817" longitude="-122.74576" azimuth="160"/>
		<base name="POR074_C" frequency="2583000" color="#CCFFFF" baseid="00000200016B" latitude="45.419817" longitude="-122.74576" azimuth="260"/>
		<base name="POR075_A" frequency="2553000" color="#FF33CC" baseid="000002000183" latitude="45.463069" longitude="-122.7017" azimuth="40"/>
		<base name="POR075_B" frequency="2573000" color="#FFFF99" baseid="000002000181" latitude="45.463069" longitude="-122.7017" azimuth="150"/>
		<base name="POR075_C" frequency="2583000" color="#CCFFFF" baseid="000002000182" latitude="45.463069" longitude="-122.7017" azimuth="280"/>
	</bases>
</config>
